{
    "Tent_Interior" : {
        "name" : "Tent_Interior",
        "filepath" : "Map_Tent_Interior.tmx",
        "portals" : [
            {
                "dest_room" : "Green_Forest",
                "dest_coords" : [12,7],
                "dest_dir" : 2,
                "is_locked" : false,
                "key" : null
            }
        ],
        "items" : ["silver coin"],
        "npcs" : [
            {
                "name" : "Hungry Boy",
                "filepath" : "Resources/npc_images/npc_student.png",
                "voice_lines" :["Sandman, I'm very hungry... Can you give me some food?",
                 "Thanks for the berries! I'll eat them up quick!", "I'm so full!"],
                "item_wants" : "berry",
                "coordinates" : [3,2]
            }
        ]
    },

    "Green_Forest" : {
        "name" : "Green_Forest",
        "filepath" : "Map_Green_Forest.tmx",
        "portals" : [
            {
                "dest_room" : "Small_Dungeon_1",
                "dest_coords" : [3,8],
                "dest_dir" : 0,
                "is_locked" : false,
                "key" : null
            },
            {
                "dest_room" : "Tent_Interior",
                "dest_coords" : [10,1],
                "dest_dir" : 2,
                "is_locked" : false,
                "key" : null
            }           
        ],
        "items" : ["campfire logs"],
        "npcs" : [
            {
                "name" : "Guard",
                "filepath" : "Resources/npc_images/npc_guard.png",
                "voice_lines" : ["Sandman, I'm too scared to go into the dungeon without my axe.","Thanks! Where'd you find it?",
                "I'm almost ready to go in...I promise"],
                "item_wants" : "battleaxe",
                "coordinates" : [23,4]
            }
        ]
    },

    "Small_Dungeon_1" : {
        "name" : "Small_Dungeon_1",
        "filepath" : "Map_Small_Dungeon_1.tmx",
        "portals" : [
            {
                "dest_room" : "Small_Dungeon_2",
                "dest_coords" : [9,1],
                "dest_dir" : 2,
                "is_locked" : false,
                "key" : null
            },
            {
                "dest_room" : "Green_Forest",
                "dest_coords" : [26,1],
                "dest_dir" : 2,
                "is_locked" : false,
                "key" : null
            }            
        ],
        "items" : ["skull"],
        "npcs" : [
            {
                "name" : "Mysterious Man",
                "filepath" : "Resources/npc_images/npc_mysterous_guy.png",
                "voice_lines" : ["Sandman, I need more riches to fill my chest!","Oh, this coin is perfect!", "I love my shiny new coin! If only I had some more..."],
                "item_wants" : "silver coin",
                "coordinates" : [5,2]
            }
        ]
    },

    "Small_Dungeon_2" : {
        "name" : "Small_Dungeon_2",
        "filepath" : "Map_Small_Dungeon_2.tmx",
        "portals" : [
            {
                "dest_room" : "Farmlands_2",
                "dest_coords" : [13,14],
                "dest_dir" : 0,
                "is_locked" : false,
                "key" : null
            },
            {
                "dest_room" : "Small_Dungeon_1",
                "dest_coords" : [3,1],
                "dest_dir" : 2,
                "is_locked" : false,
                "key" : null
            }            
        ],
        "items" : ["gold dagger"],
        "npcs" : [
            {
                "name" : "Skelly",
                "filepath" : "Resources/npc_images/npc_skelly.png",
                "voice_lines" : ["Sandman, I need to find my best friend! He was just in that last dungeon.", "Oh, I guess he never made it out...", 
                "I'll mourn you, my friend."],
                "item_wants" : "skull",
                "coordinates" : [1,2]
            }
        ]
    },

    "Farmlands_2" : {
        "name" : "Farmlands_2",
        "filepath" : "Map_Farmlands_2.tmx",
        "portals" : [
            {
                "dest_room" : "Farmlands",
                "dest_coords" : [12,0],
                "dest_dir" : 2,
                "is_locked" : false,
                "key" : null
            },
            {
                "dest_room" : "Small_Dungeon_2",
                "dest_coords" : [3,1],
                "dest_dir" : 2,
                "is_locked" : false,
                "key" : null
            }            
        ],
        "items" : ["berry"],
        "npcs" : [
            {
                "name" : "Dog",
                "filepath" : "Resources/npc_images/npc_dog.png",
                "voice_lines" : ["Sandman, I'm in the mood to roll around in something smelly, got anything? ARF","Wow, this is perfect! ARF", 
                "ARF ARF ARF"],
                "item_wants" : "manure",
                "coordinates" : [16,9]
            }
        ]
    },

    "Farmlands" : {
        "name" : "Farmlands",
        "filepath" : "Map_Farmlands.tmx",
        "portals" : [
            {
                "dest_room" : "Farmlands_2",
                "dest_coords" : [4,0],
                "dest_dir" : 2,
                "is_locked" : false,
                "key" : null
            },
            {
                "dest_room" : "Barn_Interior",
                "dest_coords" : [6,6],
                "dest_dir" : 2,
                "is_locked" : false,
                "key" : null
            }            
        ],
        "items" : ["manure"],
        "npcs" : [
            {
                "name" : "Random Dude",
                "filepath" : "Resources/npc_images/npc_male.png",
                "voice_lines" : ["Sandman, I'm so cold! Can you help me start a fire?","Oh good, firewood!", "Mmmm, nice and toasty"],
                "item_wants" : "campfire logs",
                "coordinates" : [22,4]
            }
        ]
    },

    "Barn_Interior" : {
        "name" : "Barn_Interior",
        "filepath" : "Map_Barn_Interior.tmx",
        "portals" : [
            {
                "dest_room" : "Farmlands",
                "dest_coords" : [17,20],
                "dest_dir" : 2,
                "is_locked" : false,
                "key" : null
            }            
        ],
        "items" : ["battleaxe"],
        "npcs" : [
            {
                "name" : "Felix",
                "filepath" : "Resources/npc_images/npc_teacher.png",
                "voice_lines" : ["Sandman, I lost my grandfather's gold dagger! Have you seen it?","Thank you! Wait, it was where?", 
                "I'm sorry Grandpa, I won't lose it again"],
                "item_wants" : "gold dagger",
                "coordinates" : [2,7]
            }
        ]
    }
}